celline/__init__ copy.py
celline/__init__.py
celline/__main__.py
celline/celline_icon.png
celline/config.py
celline/interfaces.py
celline/DB/__init__.py
celline/DB/db_structure.py
celline/DB/dev/__init__.py
celline/DB/dev/handler.py
celline/DB/dev/model.py
celline/DB/handler/__init__.py
celline/DB/handler/arrayexpress.py
celline/DB/handler/cncb.py
celline/DB/handler/geo.py
celline/DB/model/__init__.py
celline/DB/model/ae_run.py
celline/DB/model/ae_sample.py
celline/DB/model/ae_study.py
celline/DB/model/cncb_cra.py
celline/DB/model/cncb_crr.py
celline/DB/model/cncb_prjca.py
celline/DB/model/sra_gse.py
celline/DB/model/sra_gsm.py
celline/DB/model/sra_srr.py
celline/DB/model/transcriptome.py
celline/DB/obs/geo.py
celline/DB/utils/magetab_parser.py
celline/R/integrate.R
celline/api/__init__.py
celline/api/main.py
celline/api/simple.py
celline/api/standalone.py
celline/cli/__init__.py
celline/cli/commands.py
celline/cli/enhanced_invoker.py
celline/cli/interactive.py
celline/cli/invoker.py
celline/cli/main.py
celline/cli/registry.py
celline/cli/start_api.py
celline/cli/start_simple_api.py
celline/data/__init__.py
celline/data/ggplot.py
celline/data/seurat.py
celline/data/hook/loadSeurat.R
celline/data/markers/__cell_cycle_markers.tsv
celline/data/markers/__markers.tsv
celline/data/markers/__root_markers.tsv
celline/decorators/__init__.py
celline/decorators/classdecorators.py
celline/frontend/.gitignore
celline/frontend/README.md
celline/frontend/babel.config.js
celline/frontend/jsconfig.json
celline/frontend/package-lock.json
celline/frontend/package.json
celline/frontend/replacer.py
celline/frontend/template.vue
celline/frontend/tsconfig.json
celline/frontend/vue.config.js
celline/frontend/yarn.lock
celline/frontend/public/favicon.ico
celline/frontend/public/index.html
celline/frontend/src/App.vue
celline/frontend/src/main.js
celline/frontend/src/main.ts
celline/frontend/src/assets/logo.png
celline/frontend/src/components/HelloWorld.vue
celline-1.0.2.dist-info/METADATA
celline-1.0.2.dist-info/WHEEL
celline-1.0.2.dist-info/entry_points.txt
celline-1.0.2.dist-info/licenses/LICENSE
celline-1.0.2.dist-info/RECORD
