Metadata-Version: 2.4
Name: celline
Version: 1.0.2
Summary: Celline - A comprehensive toolkit for single-cell RNA sequencing data analysis
Author-email: YUYA556223 <yuya.sato.jp@gmail.com>
License: MIT
License-File: LICENSE
Requires-Python: >=3.10
Requires-Dist: argparse>=1.4.0
Requires-Dist: continuousvi>=0.1.5
Requires-Dist: fastapi>=0.104.0
Requires-Dist: harmonypy>=0.0.10
Requires-Dist: inquirer>=3.4.0
Requires-Dist: iprogress>=0.4
Requires-Dist: ipywidgets>=8.1.5
Requires-Dist: multipledispatch>=1.0.0
Requires-Dist: openai>=1.98.0
Requires-Dist: pandas>=2.2.3
Requires-Dist: polars>=1.26.0
Requires-Dist: pyarrow>=19.0.1
Requires-Dist: pydantic>=2.5.0
Requires-Dist: pyper>=1.1.2
Requires-Dist: pysradb>=2.2.2
Requires-Dist: pyyaml>=6.0.2
Requires-Dist: requests-html>=0.10.0
Requires-Dist: requests>=2.31.0
Requires-Dist: rich>=14.0.0
Requires-Dist: scanpy>=1.11.1
Requires-Dist: scikit-misc>=0.5.1
Requires-Dist: scrublet>=0.2.3
Requires-Dist: toml>=0.10.2
Requires-Dist: tqdm>=4.67.1
Requires-Dist: uvicorn>=0.24.0
Requires-Dist: varname>=0.14.0
